matemuzb/__init__.py
matemuzb-0.0.2.dist-info/METADATA
matemuzb-0.0.2.dist-info/WHEEL
matemuzb-0.0.2.dist-info/top_level.txt
matemuzb-0.0.2.dist-info/RECORD
