Metadata-Version: 2.1
Name: matemuzb
Version: 0.0.2
Summary: Bu kutubxona ishlatilmaydi
Author: Sarvar
Author-email: sarvarsaydullayev185@gmail.com
